boxabar/__init__.py
boxabar/exceptions.py
boxabar/message.py
boxabar/messengers.py
boxabar/utils.py
boxabar-0.1.0.dist-info/METADATA
boxabar-0.1.0.dist-info/WHEEL
boxabar-0.1.0.dist-info/top_level.txt
boxabar-0.1.0.dist-info/RECORD
