Metadata-Version: 2.2
Name: boxabar
Version: 0.1.0
Summary: Turli xil xabar yuborish usullarini qo'llab-quvvatlovchi Python kutubxonasi
Home-page: https://github.com/jaloliddinswe/boxabar
Author: Jaloliddin SWE
Author-email: jaloliddinswe@gmail.com
Classifier: Programming Language :: Python :: 3
Classifier: License :: OSI Approved :: MIT License
Classifier: Operating System :: OS Independent
Requires-Python: >=3.6
Dynamic: author
Dynamic: author-email
Dynamic: classifier
Dynamic: description
Dynamic: description-content-type
Dynamic: home-page
Dynamic: requires-python
Dynamic: summary
